{"1": {"event_main": "माघे संक्रान्ति", "extra_1": "", "extra_2": "", "date_np": "1", "date_en": "15", "tithi": "चतुर्थी", "week_day": "Wed"}, "2": {"event_main": "", "extra_1": "", "extra_2": "", "date_np": "2", "date_en": "16", "tithi": "पुर्णिमा", "week_day": "Thu"}, "3": {"event_main": "", "extra_1": "", "extra_2": "", "date_np": "3", "date_en": "17", "tithi": "प्रतिपदा", "week_day": "Fri"}, "4": {"event_main": "", "extra_1": "", "extra_2": "", "date_np": "4", "date_en": "18", "tithi": "दृतीया", "week_day": "Sat"}, "5": {"event_main": "", "extra_1": "", "extra_2": "", "date_np": "5", "date_en": "19", "tithi": "तृतीया", "week_day": "Sun"}, "6": {"event_main": "", "extra_1": "", "extra_2": "", "date_np": "6", "date_en": "20", "tithi": "चतुर्थी", "week_day": "Mon"}, "7": {"event_main": "", "extra_1": "", "extra_2": "", "date_np": "7", "date_en": "21", "tithi": "पञ्चमी", "week_day": "Tue"}, "8": {"event_main": "", "extra_1": "", "extra_2": "", "date_np": "8", "date_en": "22", "tithi": "षष्ठी", "week_day": "Wed"}, "9": {"event_main": "", "extra_1": "", "extra_2": "", "date_np": "9", "date_en": "23", "tithi": "सप्तमी", "week_day": "Thu"}, "10": {"event_main": "", "extra_1": "", "extra_2": "", "date_np": "10", "date_en": "24", "tithi": "अष्टमी", "week_day": "Fri"}, "11": {"event_main": "", "extra_1": "", "extra_2": "", "date_np": "11", "date_en": "25", "tithi": "नवमी", "week_day": "Sat"}, "12": {"event_main": "", "extra_1": "", "extra_2": "", "date_np": "12", "date_en": "26", "tithi": "दशमी", "week_day": "Sun"}, "13": {"event_main": "", "extra_1": "", "extra_2": "", "date_np": "13", "date_en": "27", "tithi": "एकादशी", "week_day": "Mon"}, "14": {"event_main": "", "extra_1": "", "extra_2": "", "date_np": "14", "date_en": "28", "tithi": "द्वादशी", "week_day": "Tue"}, "15": {"event_main": "", "extra_1": "", "extra_2": "", "date_np": "15", "date_en": "29", "tithi": "त्रायोदशी चतुर्दशि", "week_day": "Wed"}, "16": {"event_main": "शहीद दिवस", "extra_1": "", "extra_2": "", "date_np": "16", "date_en": "30", "tithi": "औसी", "week_day": "Thu"}, "17": {"event_main": "सोनाम ल्होसार", "extra_1": "", "extra_2": "", "date_np": "17", "date_en": "31", "tithi": "प्रतिपदा", "week_day": "Fri"}, "18": {"event_main": "", "extra_1": "", "extra_2": "", "date_np": "18", "date_en": "1", "tithi": "दृतीया", "week_day": "Sat"}, "19": {"event_main": "", "extra_1": "", "extra_2": "", "date_np": "19", "date_en": "2", "tithi": "तृतीया", "week_day": "Sun"}, "20": {"event_main": "", "extra_1": "", "extra_2": "", "date_np": "20", "date_en": "3", "tithi": "चतुर्थी", "week_day": "Mon"}, "21": {"event_main": "क्यान्सर दिवस", "extra_1": "", "extra_2": "", "date_np": "21", "date_en": "4", "tithi": "Panchami", "week_day": "Tue"}, "22": {"event_main": "", "extra_1": "", "extra_2": "", "date_np": "22", "date_en": "5", "tithi": "षष्ठी", "week_day": "Wed"}, "23": {"event_main": "", "extra_1": "", "extra_2": "", "date_np": "23", "date_en": "6", "tithi": "सप्तमी", "week_day": "Thu"}, "24": {"event_main": "", "extra_1": "", "extra_2": "", "date_np": "24", "date_en": "7", "tithi": "अष्टमी", "week_day": "Fri"}, "25": {"event_main": "", "extra_1": "", "extra_2": "", "date_np": "25", "date_en": "8", "tithi": "नवमी", "week_day": "Sat"}, "26": {"event_main": "", "extra_1": "", "extra_2": "", "date_np": "26", "date_en": "9", "tithi": "दशमी", "week_day": "Sun"}, "27": {"event_main": "भिमा एकादशी", "extra_1": "", "extra_2": "", "date_np": "27", "date_en": "10", "tithi": "एकादशी", "week_day": "Mon"}, "28": {"event_main": "", "extra_1": "", "extra_2": "", "date_np": "28", "date_en": "11", "tithi": "द्वादशी", "week_day": "Tue"}, "29": {"event_main": "", "extra_1": "", "extra_2": "", "date_np": "29", "date_en": "12", "tithi": "त्रायोदशी", "week_day": "Wed"}}